lgraph/__init__.py
lgraph/edge.py
lgraph/lgraph.py
lgraph/vertex.py
l_graph-0.2.2.dist-info/LICENSE
l_graph-0.2.2.dist-info/METADATA
l_graph-0.2.2.dist-info/WHEEL
l_graph-0.2.2.dist-info/top_level.txt
l_graph-0.2.2.dist-info/RECORD
