Metadata-Version: 2.1
Name: l-graph
Version: 0.2.2
Summary: Python module for working with L-graphs
Home-page: https://github.com/rudanov/lgraph
Author: Dmitry Rudanov
Author-email: rudanov.d@gmail.com
License: UNKNOWN
Platform: UNKNOWN
Classifier: Programming Language :: Python :: 3
Classifier: License :: OSI Approved :: MIT License
Classifier: Operating System :: OS Independent
